{
  "guid": "00b66da2-73f5-4c17-ae28-85cde8de1662",
  "title": "Embodied large language models enable robots to complete complex tasks in unpredictable environments",
  "itunes_title": "Embodied large language models enable robots to complete complex tasks in unpredictable environments",
  "description": "<p>https://www.nature.com/articles/s42256-025-01005-x</p>",
  "pub_date": "Sun, 30 Mar 2025 17:24:23 GMT",
  "duration_seconds": 732,
  "episode_number": 30,
  "episode_type": "full",
  "explicit": "false",
  "enclosure_filename": "030-embodied-large-language-models-enable-robots-to-complete.mp3",
  "enclosure_length_bytes": 11712514,
  "source": "migrated_from_rss.com"
}