{
  "guid": "ef6b64ae-650d-4e35-bfbd-88e0168f0b2c",
  "title": "The impact of CD3 affinity-attenuation on T cell engaging bispecific antibodies: is it really that simple?",
  "itunes_title": "The impact of CD3 affinity-attenuation on T cell engaging bispecific antibodies: is it really that simple?",
  "description": "<p>DOI: 10.1080/17460441.2025.2522088</p>",
  "pub_date": "Fri, 12 Sep 2025 23:13:15 GMT",
  "duration_seconds": 1022,
  "episode_number": 52,
  "episode_type": "full",
  "explicit": "false",
  "enclosure_filename": "052-the-impact-of-cd3-affinity-attenuation-on-t-cell-engaging.mp3",
  "enclosure_length_bytes": 16364075,
  "source": "migrated_from_rss.com"
}